[
  {
    "title": "Introduction",
    "kind": "link",
    "source_url": "https://fluss.incubator.apache.org/docs/",
    "anchor": "index",
    "virtual_path": "docs/index.md"
  },
  {
    "title": "Quickstart",
    "kind": "link",
    "source_url": "https://fluss.incubator.apache.org/docs/quickstart/flink/",
    "anchor": "quickstart-flink",
    "virtual_path": "docs/quickstart/flink/index.md",
    "children": [
      {
        "title": "Real-Time Analytics with Flink",
        "kind": "link",
        "source_url": "https://fluss.incubator.apache.org/docs/quickstart/flink/",
        "anchor": "quickstart-flink",
        "virtual_path": "docs/quickstart/flink/index.md"
      },
      {
        "title": "Building a Streaming Lakehouse",
        "kind": "link",
        "source_url": "https://fluss.incubator.apache.org/docs/quickstart/lakehouse/",
        "anchor": "quickstart-lakehouse",
        "virtual_path": "docs/quickstart/lakehouse/index.md"
      },
      {
        "title": "Secure Your Fluss Cluster",
        "kind": "link",
        "source_url": "https://fluss.incubator.apache.org/docs/quickstart/security/",
        "anchor": "quickstart-security",
        "virtual_path": "docs/quickstart/security/index.md"
      }
    ]
  },
  {
    "title": "Concepts",
    "kind": "link",
    "source_url": "https://fluss.incubator.apache.org/docs/concepts/architecture/",
    "anchor": "concepts-architecture",
    "virtual_path": "docs/concepts/architecture/index.md",
    "children": [
      {
        "title": "Architecture",
        "kind": "link",
        "source_url": "https://fluss.incubator.apache.org/docs/concepts/architecture/",
        "anchor": "concepts-architecture",
        "virtual_path": "docs/concepts/architecture/index.md"
      }
    ]
  },
  {
    "title": "Installation & Deployment",
    "kind": "link",
    "source_url": "https://fluss.incubator.apache.org/docs/install-deploy/overview/",
    "anchor": "install-deploy-overview",
    "virtual_path": "docs/install-deploy/overview/index.md",
    "children": [
      {
        "title": "Overview",
        "kind": "link",
        "source_url": "https://fluss.incubator.apache.org/docs/install-deploy/overview/",
        "anchor": "install-deploy-overview",
        "virtual_path": "docs/install-deploy/overview/index.md"
      },
      {
        "title": "Deploying Local Cluster",
        "kind": "link",
        "source_url": "https://fluss.incubator.apache.org/docs/install-deploy/deploying-local-cluster/",
        "anchor": "install-deploy-deploying-local-cluster",
        "virtual_path": "docs/install-deploy/deploying-local-cluster/index.md"
      },
      {
        "title": "Deploying Distributed Cluster",
        "kind": "link",
        "source_url": "https://fluss.incubator.apache.org/docs/install-deploy/deploying-distributed-cluster/",
        "anchor": "install-deploy-deploying-distributed-cluster",
        "virtual_path": "docs/install-deploy/deploying-distributed-cluster/index.md"
      },
      {
        "title": "Deploying with Docker",
        "kind": "link",
        "source_url": "https://fluss.incubator.apache.org/docs/install-deploy/deploying-with-docker/",
        "anchor": "install-deploy-deploying-with-docker",
        "virtual_path": "docs/install-deploy/deploying-with-docker/index.md"
      },
      {
        "title": "Deploying with Helm Charts",
        "kind": "link",
        "source_url": "https://fluss.incubator.apache.org/docs/install-deploy/deploying-with-helm/",
        "anchor": "install-deploy-deploying-with-helm",
        "virtual_path": "docs/install-deploy/deploying-with-helm/index.md"
      }
    ]
  },
  {
    "title": "Table Design",
    "kind": "category",
    "source_url": "https://fluss.incubator.apache.org/docs/table-design/overview/",
    "anchor": "table-design-overview",
    "virtual_path": "docs/table-design/overview/index.md",
    "children": [
      {
        "title": "Overview",
        "kind": "link",
        "source_url": "https://fluss.incubator.apache.org/docs/table-design/overview/",
        "anchor": "table-design-overview",
        "virtual_path": "docs/table-design/overview/index.md"
      },
      {
        "title": "Table Types",
        "kind": "link",
        "source_url": "https://fluss.incubator.apache.org/docs/table-design/table-types/log-table/",
        "anchor": "table-design-table-types-log-table",
        "virtual_path": "docs/table-design/table-types/log-table/index.md",
        "children": [
          {
            "title": "Log Table",
            "kind": "link",
            "source_url": "https://fluss.incubator.apache.org/docs/table-design/table-types/log-table/",
            "anchor": "table-design-table-types-log-table",
            "virtual_path": "docs/table-design/table-types/log-table/index.md"
          },
          {
            "title": "Primary Key Table",
            "kind": "link",
            "source_url": "https://fluss.incubator.apache.org/docs/table-design/table-types/pk-table/",
            "anchor": "table-design-table-types-pk-table",
            "virtual_path": "docs/table-design/table-types/pk-table/index.md"
          }
        ]
      },
      {
        "title": "Merge Engines",
        "kind": "category",
        "source_url": "https://fluss.incubator.apache.org/docs/table-design/merge-engines/",
        "anchor": "table-design-merge-engines",
        "virtual_path": "docs/table-design/merge-engines/index.md",
        "children": [
          {
            "title": "Default (LastRow)",
            "kind": "link",
            "source_url": "https://fluss.incubator.apache.org/docs/table-design/merge-engines/default/",
            "anchor": "table-design-merge-engines-default",
            "virtual_path": "docs/table-design/merge-engines/default/index.md"
          },
          {
            "title": "FirstRow",
            "kind": "link",
            "source_url": "https://fluss.incubator.apache.org/docs/table-design/merge-engines/first-row/",
            "anchor": "table-design-merge-engines-first-row",
            "virtual_path": "docs/table-design/merge-engines/first-row/index.md"
          },
          {
            "title": "Versioned",
            "kind": "link",
            "source_url": "https://fluss.incubator.apache.org/docs/table-design/merge-engines/versioned/",
            "anchor": "table-design-merge-engines-versioned",
            "virtual_path": "docs/table-design/merge-engines/versioned/index.md"
          },
          {
            "title": "Aggregation",
            "kind": "link",
            "source_url": "https://fluss.incubator.apache.org/docs/table-design/merge-engines/aggregation/",
            "anchor": "table-design-merge-engines-aggregation",
            "virtual_path": "docs/table-design/merge-engines/aggregation/index.md"
          }
        ]
      },
      {
        "title": "Virtual Tables",
        "kind": "link",
        "source_url": "https://fluss.incubator.apache.org/docs/table-design/virtual-tables/",
        "anchor": "table-design-virtual-tables",
        "virtual_path": "docs/table-design/virtual-tables/index.md"
      },
      {
        "title": "Data Distribution",
        "kind": "link",
        "source_url": "https://fluss.incubator.apache.org/docs/table-design/data-distribution/bucketing/",
        "anchor": "table-design-data-distribution-bucketing",
        "virtual_path": "docs/table-design/data-distribution/bucketing/index.md",
        "children": [
          {
            "title": "Bucketing",
            "kind": "link",
            "source_url": "https://fluss.incubator.apache.org/docs/table-design/data-distribution/bucketing/",
            "anchor": "table-design-data-distribution-bucketing",
            "virtual_path": "docs/table-design/data-distribution/bucketing/index.md"
          },
          {
            "title": "Partitioning",
            "kind": "link",
            "source_url": "https://fluss.incubator.apache.org/docs/table-design/data-distribution/partitioning/",
            "anchor": "table-design-data-distribution-partitioning",
            "virtual_path": "docs/table-design/data-distribution/partitioning/index.md"
          },
          {
            "title": "TTL",
            "kind": "link",
            "source_url": "https://fluss.incubator.apache.org/docs/table-design/data-distribution/ttl/",
            "anchor": "table-design-data-distribution-ttl",
            "virtual_path": "docs/table-design/data-distribution/ttl/index.md"
          }
        ]
      },
      {
        "title": "Data Formats",
        "kind": "link",
        "source_url": "https://fluss.incubator.apache.org/docs/table-design/data-formats/",
        "anchor": "table-design-data-formats",
        "virtual_path": "docs/table-design/data-formats/index.md"
      },
      {
        "title": "Data Types",
        "kind": "link",
        "source_url": "https://fluss.incubator.apache.org/docs/table-design/data-types/",
        "anchor": "table-design-data-types",
        "virtual_path": "docs/table-design/data-types/index.md"
      }
    ]
  },
  {
    "title": "Engine Flink",
    "kind": "link",
    "source_url": "https://fluss.incubator.apache.org/docs/engine-flink/getting-started/",
    "anchor": "engine-flink-getting-started",
    "virtual_path": "docs/engine-flink/getting-started/index.md",
    "children": [
      {
        "title": "Getting Started",
        "kind": "link",
        "source_url": "https://fluss.incubator.apache.org/docs/engine-flink/getting-started/",
        "anchor": "engine-flink-getting-started",
        "virtual_path": "docs/engine-flink/getting-started/index.md"
      },
      {
        "title": "DDL",
        "kind": "link",
        "source_url": "https://fluss.incubator.apache.org/docs/engine-flink/ddl/",
        "anchor": "engine-flink-ddl",
        "virtual_path": "docs/engine-flink/ddl/index.md"
      },
      {
        "title": "Procedures",
        "kind": "link",
        "source_url": "https://fluss.incubator.apache.org/docs/engine-flink/procedures/",
        "anchor": "engine-flink-procedures",
        "virtual_path": "docs/engine-flink/procedures/index.md"
      },
      {
        "title": "Writes",
        "kind": "link",
        "source_url": "https://fluss.incubator.apache.org/docs/engine-flink/writes/",
        "anchor": "engine-flink-writes",
        "virtual_path": "docs/engine-flink/writes/index.md"
      },
      {
        "title": "Reads",
        "kind": "link",
        "source_url": "https://fluss.incubator.apache.org/docs/engine-flink/reads/",
        "anchor": "engine-flink-reads",
        "virtual_path": "docs/engine-flink/reads/index.md"
      },
      {
        "title": "Lookups",
        "kind": "link",
        "source_url": "https://fluss.incubator.apache.org/docs/engine-flink/lookups/",
        "anchor": "engine-flink-lookups",
        "virtual_path": "docs/engine-flink/lookups/index.md"
      },
      {
        "title": "Delta Joins",
        "kind": "link",
        "source_url": "https://fluss.incubator.apache.org/docs/engine-flink/delta-joins/",
        "anchor": "engine-flink-delta-joins",
        "virtual_path": "docs/engine-flink/delta-joins/index.md"
      },
      {
        "title": "DataStream API",
        "kind": "link",
        "source_url": "https://fluss.incubator.apache.org/docs/engine-flink/datastream/",
        "anchor": "engine-flink-datastream",
        "virtual_path": "docs/engine-flink/datastream/index.md"
      },
      {
        "title": "Connector Options",
        "kind": "link",
        "source_url": "https://fluss.incubator.apache.org/docs/engine-flink/options/",
        "anchor": "engine-flink-options",
        "virtual_path": "docs/engine-flink/options/index.md"
      }
    ]
  },
  {
    "title": "Engine Spark",
    "kind": "link",
    "source_url": "https://fluss.incubator.apache.org/docs/engine-spark/getting-started/",
    "anchor": "engine-spark-getting-started",
    "virtual_path": "docs/engine-spark/getting-started/index.md",
    "children": [
      {
        "title": "Getting Started",
        "kind": "link",
        "source_url": "https://fluss.incubator.apache.org/docs/engine-spark/getting-started/",
        "anchor": "engine-spark-getting-started",
        "virtual_path": "docs/engine-spark/getting-started/index.md"
      },
      {
        "title": "DDL",
        "kind": "link",
        "source_url": "https://fluss.incubator.apache.org/docs/engine-spark/ddl/",
        "anchor": "engine-spark-ddl",
        "virtual_path": "docs/engine-spark/ddl/index.md"
      },
      {
        "title": "Procedures",
        "kind": "link",
        "source_url": "https://fluss.incubator.apache.org/docs/engine-spark/procedures/",
        "anchor": "engine-spark-procedures",
        "virtual_path": "docs/engine-spark/procedures/index.md"
      },
      {
        "title": "Writes",
        "kind": "link",
        "source_url": "https://fluss.incubator.apache.org/docs/engine-spark/writes/",
        "anchor": "engine-spark-writes",
        "virtual_path": "docs/engine-spark/writes/index.md"
      },
      {
        "title": "Reads",
        "kind": "link",
        "source_url": "https://fluss.incubator.apache.org/docs/engine-spark/reads/",
        "anchor": "engine-spark-reads",
        "virtual_path": "docs/engine-spark/reads/index.md"
      },
      {
        "title": "Structured Streaming",
        "kind": "link",
        "source_url": "https://fluss.incubator.apache.org/docs/engine-spark/structured-streaming/",
        "anchor": "engine-spark-structured-streaming",
        "virtual_path": "docs/engine-spark/structured-streaming/index.md"
      },
      {
        "title": "Connector Options",
        "kind": "link",
        "source_url": "https://fluss.incubator.apache.org/docs/engine-spark/options/",
        "anchor": "engine-spark-options",
        "virtual_path": "docs/engine-spark/options/index.md"
      }
    ]
  },
  {
    "title": "Streaming Lakehouse",
    "kind": "link",
    "source_url": "https://fluss.incubator.apache.org/docs/streaming-lakehouse/overview/",
    "anchor": "streaming-lakehouse-overview",
    "virtual_path": "docs/streaming-lakehouse/overview/index.md",
    "children": [
      {
        "title": "Lakehouse Overview",
        "kind": "link",
        "source_url": "https://fluss.incubator.apache.org/docs/streaming-lakehouse/overview/",
        "anchor": "streaming-lakehouse-overview",
        "virtual_path": "docs/streaming-lakehouse/overview/index.md"
      },
      {
        "title": "Integrate Data Lakes",
        "kind": "category",
        "source_url": "https://fluss.incubator.apache.org/docs/streaming-lakehouse/integrate-data-lakes/paimon/",
        "anchor": "streaming-lakehouse-integrate-data-lakes-paimon",
        "virtual_path": "docs/streaming-lakehouse/integrate-data-lakes/paimon/index.md",
        "children": [
          {
            "title": "Paimon",
            "kind": "link",
            "source_url": "https://fluss.incubator.apache.org/docs/streaming-lakehouse/integrate-data-lakes/paimon/",
            "anchor": "streaming-lakehouse-integrate-data-lakes-paimon",
            "virtual_path": "docs/streaming-lakehouse/integrate-data-lakes/paimon/index.md"
          },
          {
            "title": "Iceberg",
            "kind": "link",
            "source_url": "https://fluss.incubator.apache.org/docs/streaming-lakehouse/integrate-data-lakes/iceberg/",
            "anchor": "streaming-lakehouse-integrate-data-lakes-iceberg",
            "virtual_path": "docs/streaming-lakehouse/integrate-data-lakes/iceberg/index.md"
          },
          {
            "title": "Lance",
            "kind": "link",
            "source_url": "https://fluss.incubator.apache.org/docs/streaming-lakehouse/integrate-data-lakes/lance/",
            "anchor": "streaming-lakehouse-integrate-data-lakes-lance",
            "virtual_path": "docs/streaming-lakehouse/integrate-data-lakes/lance/index.md"
          }
        ]
      }
    ]
  },
  {
    "title": "Maintenance",
    "kind": "link",
    "source_url": "https://fluss.incubator.apache.org/docs/maintenance/configuration/",
    "anchor": "maintenance-configuration",
    "virtual_path": "docs/maintenance/configuration/index.md",
    "children": [
      {
        "title": "Configuration",
        "kind": "link",
        "source_url": "https://fluss.incubator.apache.org/docs/maintenance/configuration/",
        "anchor": "maintenance-configuration",
        "virtual_path": "docs/maintenance/configuration/index.md"
      },
      {
        "title": "File Systems",
        "kind": "link",
        "source_url": "https://fluss.incubator.apache.org/docs/maintenance/filesystems/overview/",
        "anchor": "maintenance-filesystems-overview",
        "virtual_path": "docs/maintenance/filesystems/overview/index.md",
        "children": [
          {
            "title": "Overview",
            "kind": "link",
            "source_url": "https://fluss.incubator.apache.org/docs/maintenance/filesystems/overview/",
            "anchor": "maintenance-filesystems-overview",
            "virtual_path": "docs/maintenance/filesystems/overview/index.md"
          },
          {
            "title": "HDFS",
            "kind": "link",
            "source_url": "https://fluss.incubator.apache.org/docs/maintenance/filesystems/hdfs/",
            "anchor": "maintenance-filesystems-hdfs",
            "virtual_path": "docs/maintenance/filesystems/hdfs/index.md"
          },
          {
            "title": "Aliyun OSS",
            "kind": "link",
            "source_url": "https://fluss.incubator.apache.org/docs/maintenance/filesystems/oss/",
            "anchor": "maintenance-filesystems-oss",
            "virtual_path": "docs/maintenance/filesystems/oss/index.md"
          },
          {
            "title": "Amazon S3",
            "kind": "link",
            "source_url": "https://fluss.incubator.apache.org/docs/maintenance/filesystems/s3/",
            "anchor": "maintenance-filesystems-s3",
            "virtual_path": "docs/maintenance/filesystems/s3/index.md"
          },
          {
            "title": "Azure Blob Storage",
            "kind": "link",
            "source_url": "https://fluss.incubator.apache.org/docs/maintenance/filesystems/azure/",
            "anchor": "maintenance-filesystems-azure",
            "virtual_path": "docs/maintenance/filesystems/azure/index.md"
          },
          {
            "title": "HuaweiCloud OBS",
            "kind": "link",
            "source_url": "https://fluss.incubator.apache.org/docs/maintenance/filesystems/obs/",
            "anchor": "maintenance-filesystems-obs",
            "virtual_path": "docs/maintenance/filesystems/obs/index.md"
          }
        ]
      },
      {
        "title": "Tiered Storage",
        "kind": "link",
        "source_url": "https://fluss.incubator.apache.org/docs/maintenance/tiered-storage/overview/",
        "anchor": "maintenance-tiered-storage-overview",
        "virtual_path": "docs/maintenance/tiered-storage/overview/index.md",
        "children": [
          {
            "title": "Overview",
            "kind": "link",
            "source_url": "https://fluss.incubator.apache.org/docs/maintenance/tiered-storage/overview/",
            "anchor": "maintenance-tiered-storage-overview",
            "virtual_path": "docs/maintenance/tiered-storage/overview/index.md"
          },
          {
            "title": "Remote Storage",
            "kind": "link",
            "source_url": "https://fluss.incubator.apache.org/docs/maintenance/tiered-storage/remote-storage/",
            "anchor": "maintenance-tiered-storage-remote-storage",
            "virtual_path": "docs/maintenance/tiered-storage/remote-storage/index.md"
          },
          {
            "title": "Lakehouse Storage",
            "kind": "link",
            "source_url": "https://fluss.incubator.apache.org/docs/maintenance/tiered-storage/lakehouse-storage/",
            "anchor": "maintenance-tiered-storage-lakehouse-storage",
            "virtual_path": "docs/maintenance/tiered-storage/lakehouse-storage/index.md"
          }
        ]
      },
      {
        "title": "Observability",
        "kind": "link",
        "source_url": "https://fluss.incubator.apache.org/docs/maintenance/observability/quickstart/",
        "anchor": "maintenance-observability-quickstart",
        "virtual_path": "docs/maintenance/observability/quickstart/index.md",
        "children": [
          {
            "title": "Quickstart Guides",
            "kind": "link",
            "source_url": "https://fluss.incubator.apache.org/docs/maintenance/observability/quickstart/",
            "anchor": "maintenance-observability-quickstart",
            "virtual_path": "docs/maintenance/observability/quickstart/index.md"
          },
          {
            "title": "Metric Reporters",
            "kind": "link",
            "source_url": "https://fluss.incubator.apache.org/docs/maintenance/observability/metric-reporters/",
            "anchor": "maintenance-observability-metric-reporters",
            "virtual_path": "docs/maintenance/observability/metric-reporters/index.md"
          },
          {
            "title": "Monitor Metrics",
            "kind": "link",
            "source_url": "https://fluss.incubator.apache.org/docs/maintenance/observability/monitor-metrics/",
            "anchor": "maintenance-observability-monitor-metrics",
            "virtual_path": "docs/maintenance/observability/monitor-metrics/index.md"
          },
          {
            "title": "Logging",
            "kind": "link",
            "source_url": "https://fluss.incubator.apache.org/docs/maintenance/observability/logging/",
            "anchor": "maintenance-observability-logging",
            "virtual_path": "docs/maintenance/observability/logging/index.md"
          }
        ]
      },
      {
        "title": "Operations",
        "kind": "category",
        "source_url": "https://fluss.incubator.apache.org/docs/maintenance/operations/updating-configs/",
        "anchor": "maintenance-operations-updating-configs",
        "virtual_path": "docs/maintenance/operations/updating-configs/index.md",
        "children": [
          {
            "title": "Updating Configs",
            "kind": "link",
            "source_url": "https://fluss.incubator.apache.org/docs/maintenance/operations/updating-configs/",
            "anchor": "maintenance-operations-updating-configs",
            "virtual_path": "docs/maintenance/operations/updating-configs/index.md"
          },
          {
            "title": "Rack-Aware Deployment",
            "kind": "link",
            "source_url": "https://fluss.incubator.apache.org/docs/maintenance/operations/racks/",
            "anchor": "maintenance-operations-racks",
            "virtual_path": "docs/maintenance/operations/racks/index.md"
          },
          {
            "title": "Rebalance",
            "kind": "link",
            "source_url": "https://fluss.incubator.apache.org/docs/maintenance/operations/rebalance/",
            "anchor": "maintenance-operations-rebalance",
            "virtual_path": "docs/maintenance/operations/rebalance/index.md"
          },
          {
            "title": "Graceful Shutdown",
            "kind": "link",
            "source_url": "https://fluss.incubator.apache.org/docs/maintenance/operations/graceful-shutdown/",
            "anchor": "maintenance-operations-graceful-shutdown",
            "virtual_path": "docs/maintenance/operations/graceful-shutdown/index.md"
          },
          {
            "title": "Upgrading and Compatibility",
            "kind": "link",
            "source_url": "https://fluss.incubator.apache.org/docs/maintenance/operations/upgrading/",
            "anchor": "maintenance-operations-upgrading",
            "virtual_path": "docs/maintenance/operations/upgrading/index.md"
          },
          {
            "title": "Upgrade Notes Archive",
            "kind": "link",
            "source_url": "https://fluss.incubator.apache.org/docs/maintenance/operations/upgrade-notes-archive/",
            "anchor": "maintenance-operations-upgrade-notes-archive",
            "virtual_path": "docs/maintenance/operations/upgrade-notes-archive/index.md"
          }
        ]
      }
    ]
  },
  {
    "title": "Security",
    "kind": "link",
    "source_url": "https://fluss.incubator.apache.org/docs/security/overview/",
    "anchor": "security-overview",
    "virtual_path": "docs/security/overview/index.md",
    "children": [
      {
        "title": "Security Overview",
        "kind": "link",
        "source_url": "https://fluss.incubator.apache.org/docs/security/overview/",
        "anchor": "security-overview",
        "virtual_path": "docs/security/overview/index.md"
      },
      {
        "title": "Authentication",
        "kind": "link",
        "source_url": "https://fluss.incubator.apache.org/docs/security/authentication/",
        "anchor": "security-authentication",
        "virtual_path": "docs/security/authentication/index.md"
      },
      {
        "title": "Authorization and ACLs",
        "kind": "link",
        "source_url": "https://fluss.incubator.apache.org/docs/security/authorization/",
        "anchor": "security-authorization",
        "virtual_path": "docs/security/authorization/index.md"
      }
    ]
  },
  {
    "title": "Fluss APIs",
    "kind": "link",
    "source_url": "https://fluss.incubator.apache.org/docs/apis/java-client/",
    "anchor": "apis-java-client",
    "virtual_path": "docs/apis/java-client/index.md",
    "children": [
      {
        "title": "Java Client",
        "kind": "link",
        "source_url": "https://fluss.incubator.apache.org/docs/apis/java-client/",
        "anchor": "apis-java-client",
        "virtual_path": "docs/apis/java-client/index.md"
      },
      {
        "title": "Client Support Matrix",
        "kind": "link",
        "source_url": "https://fluss.incubator.apache.org/docs/apis/client-support-matrix/",
        "anchor": "apis-client-support-matrix",
        "virtual_path": "docs/apis/client-support-matrix/index.md"
      }
    ]
  }
]