[
  {
    "title": "Components",
    "kind": "category",
    "children": [
      {
        "title": "HttpCore 5.4",
        "kind": "category",
        "children": [
          {
            "title": "Examples",
            "kind": "link",
            "source_url": "https://hc.apache.org/httpcomponents-core-5.4.x/examples.html",
            "anchor": "examples",
            "virtual_path": "docs/examples.md"
          },
          {
            "title": "Download",
            "kind": "link",
            "source_url": "https://hc.apache.org/httpcomponents-core-5.4.x/download.html",
            "anchor": "download",
            "virtual_path": "docs/download.md"
          }
        ]
      }
    ]
  },
  {
    "title": "Other pages",
    "kind": "category",
    "children": [
      {
        "title": "HttpCore Overview",
        "kind": "link",
        "source_url": "https://hc.apache.org/httpcomponents-core-5.4.x/",
        "anchor": "index",
        "virtual_path": "docs/index.md"
      }
    ]
  }
]