{
  "entry_url": "https://gora.apache.org/current/index.html",
  "site_prefix": "/current/",
  "site_slug": "gora_current",
  "profile": "generic",
  "combined_markdown": "combined.md",
  "page_count": 24,
  "asset_count": 4,
  "pages": [
    {
      "source_url": "https://gora.apache.org/current/api/javadoc.html",
      "title": "Gora Java Documentation ¶",
      "anchor": "api-javadoc",
      "virtual_path": "docs/api/javadoc.md",
      "profile": "generic",
      "score": 1265,
      "depth": 1
    },
    {
      "source_url": "https://gora.apache.org/current/compiler-cli.html",
      "title": "Introduction ¶",
      "anchor": "compiler-cli",
      "virtual_path": "docs/compiler-cli.md",
      "profile": "generic",
      "score": 3100,
      "depth": 1
    },
    {
      "source_url": "https://gora.apache.org/current/compiler.html",
      "title": "Introduction ¶",
      "anchor": "compiler",
      "virtual_path": "docs/compiler.md",
      "profile": "generic",
      "score": 3965,
      "depth": 1
    },
    {
      "source_url": "https://gora.apache.org/current/gora-accumulo.html",
      "title": "Apache Gora™ - Gora Accumulo Module",
      "anchor": "gora-accumulo",
      "virtual_path": "docs/gora-accumulo.md",
      "profile": "generic",
      "score": 6083,
      "depth": 1
    },
    {
      "source_url": "https://gora.apache.org/current/gora-aerospike.html",
      "title": "Apache Gora™ - Gora Aerospike Module",
      "anchor": "gora-aerospike",
      "virtual_path": "docs/gora-aerospike.md",
      "profile": "generic",
      "score": 6671,
      "depth": 1
    },
    {
      "source_url": "https://gora.apache.org/current/gora-camel.html",
      "title": "Introduction ¶",
      "anchor": "gora-camel",
      "virtual_path": "docs/gora-camel.md",
      "profile": "generic",
      "score": 12686,
      "depth": 1
    },
    {
      "source_url": "https://gora.apache.org/current/gora-cassandra.html",
      "title": "Apache Gora™ - Gora Cassandra Module",
      "anchor": "gora-cassandra",
      "virtual_path": "docs/gora-cassandra.md",
      "profile": "generic",
      "score": 10778,
      "depth": 1
    },
    {
      "source_url": "https://gora.apache.org/current/gora-conf.html",
      "title": "Apache Gora™ - Gora Configuration",
      "anchor": "gora-conf",
      "virtual_path": "docs/gora-conf.md",
      "profile": "generic",
      "score": 5113,
      "depth": 1
    },
    {
      "source_url": "https://gora.apache.org/current/gora-core.html",
      "title": "Overview ¶",
      "anchor": "gora-core",
      "virtual_path": "docs/gora-core.md",
      "profile": "generic",
      "score": 11820,
      "depth": 1
    },
    {
      "source_url": "https://gora.apache.org/current/gora-couchdb.html",
      "title": "Apache Gora™ - Gora CouchDB Module",
      "anchor": "gora-couchdb",
      "virtual_path": "docs/gora-couchdb.md",
      "profile": "generic",
      "score": 4002,
      "depth": 1
    },
    {
      "source_url": "https://gora.apache.org/current/gora-dynamodb.html",
      "title": "Apache Gora™ - Gora DynamoDB Module",
      "anchor": "gora-dynamodb",
      "virtual_path": "docs/gora-dynamodb.md",
      "profile": "generic",
      "score": 5690,
      "depth": 1
    },
    {
      "source_url": "https://gora.apache.org/current/gora-hbase.html",
      "title": "Apache Gora™ - Gora HBase Module",
      "anchor": "gora-hbase",
      "virtual_path": "docs/gora-hbase.md",
      "profile": "generic",
      "score": 7515,
      "depth": 1
    },
    {
      "source_url": "https://gora.apache.org/current/gora-ignite.html",
      "title": "Apache Gora™ - Gora Ignite Module",
      "anchor": "gora-ignite",
      "virtual_path": "docs/gora-ignite.md",
      "profile": "generic",
      "score": 6062,
      "depth": 1
    },
    {
      "source_url": "https://gora.apache.org/current/gora-jcache.html",
      "title": "Apache Gora™ - Gora JCache Module",
      "anchor": "gora-jcache",
      "virtual_path": "docs/gora-jcache.md",
      "profile": "generic",
      "score": 5308,
      "depth": 1
    },
    {
      "source_url": "https://gora.apache.org/current/gora-kudu.html",
      "title": "Apache Gora™ - Gora Kudu Module",
      "anchor": "gora-kudu",
      "virtual_path": "docs/gora-kudu.md",
      "profile": "generic",
      "score": 9276,
      "depth": 1
    },
    {
      "source_url": "https://gora.apache.org/current/gora-metamodel.html",
      "title": "Apache Gora™ - Gora MongoDB Module",
      "anchor": "gora-metamodel",
      "virtual_path": "docs/gora-metamodel.md",
      "profile": "generic",
      "score": 2191,
      "depth": 1
    },
    {
      "source_url": "https://gora.apache.org/current/gora-mongodb.html",
      "title": "Apache Gora™ - Gora MongoDB Module",
      "anchor": "gora-mongodb",
      "virtual_path": "docs/gora-mongodb.md",
      "profile": "generic",
      "score": 6203,
      "depth": 1
    },
    {
      "source_url": "https://gora.apache.org/current/gora-pig.html",
      "title": "Apache Gora™ - Gora Pig Module",
      "anchor": "gora-pig",
      "virtual_path": "docs/gora-pig.md",
      "profile": "generic",
      "score": 10663,
      "depth": 1
    },
    {
      "source_url": "https://gora.apache.org/current/gora-solr.html",
      "title": "Apache Gora™ - Gora HBase Module",
      "anchor": "gora-solr",
      "virtual_path": "docs/gora-solr.md",
      "profile": "generic",
      "score": 10368,
      "depth": 1
    },
    {
      "source_url": "https://gora.apache.org/current/gora-sql.html",
      "title": "Apache Gora™ - Gora SQL Module",
      "anchor": "gora-sql",
      "virtual_path": "docs/gora-sql.md",
      "profile": "generic",
      "score": 2051,
      "depth": 2
    },
    {
      "source_url": "https://gora.apache.org/current/index.html",
      "title": "Apache Gora™ - Gora Module Overview",
      "anchor": "index",
      "virtual_path": "docs/index.md",
      "profile": "generic",
      "score": 24386,
      "depth": 0
    },
    {
      "source_url": "https://gora.apache.org/current/overview.html",
      "title": "Apache Gora™ - Gora Module Overview",
      "anchor": "overview",
      "virtual_path": "docs/overview.md",
      "profile": "generic",
      "score": 2568,
      "depth": 2
    },
    {
      "source_url": "https://gora.apache.org/current/quickstart.html",
      "title": "Introduction ¶",
      "anchor": "quickstart",
      "virtual_path": "docs/quickstart.md",
      "profile": "generic",
      "score": 8850,
      "depth": 1
    },
    {
      "source_url": "https://gora.apache.org/current/tutorial.html",
      "title": "Gora Tutorial ¶",
      "anchor": "tutorial",
      "virtual_path": "docs/tutorial.md",
      "profile": "generic",
      "score": 79048,
      "depth": 1
    }
  ]
}